code/latch.v
module latch(input Sbar, Rbar, output Q, Qbar);
  nand LS(Q, Sbar, Qbar);
  nand LR(Qbar, Rbar, Q);
endmodule

module main;
reg Sbar;
wire Q, Qbar, Rbar;

latch latch1(Sbar, Rbar, Q, Qbar);
not N1(Rbar, Sbar);

initial
begin
  Sbar = 0;
  $monitor("%4dns monitor: Sbar=%d Rbar=%d Q=%d Qbar=%d", $stime, Sbar, Rbar, Q, Qbar);
  $dumpfile("latch.vcd"); // 輸出給 GTK wave 顯示波型
  $dumpvars;    
end

always #50 begin
  Sbar = Sbar+1;
end

initial #500 $finish;

endmodule

code/latch.vcd
$date
	Mon Oct 14 20:13:58 2013
$end
$version
	Icarus Verilog
$end
$timescale
	1s
$end
$scope module main $end
$var wire 1 ! Q $end
$var wire 1 " Qbar $end
$var wire 1 # Rbar $end
$var reg 1 $ Sbar $end
$scope module latch1 $end
$var wire 1 ! Q $end
$var wire 1 " Qbar $end
$var wire 1 # Rbar $end
$var wire 1 % Sbar $end
$upscope $end
$upscope $end
$enddefinitions $end
#0
$dumpvars
0%
0$
1#
0"
1!
$end
#50
0!
1"
0#
1$
1%
#100
0"
1!
1#
0$
0%
#150
0!
1"
0#
1$
1%
#200
0"
1!
1#
0$
0%
#250
0!
1"
0#
1$
1%
#300
0"
1!
1#
0$
0%
#350
0!
1"
0#
1$
1%
#400
0"
1!
1#
0$
0%
#450
0!
1"
0#
1$
1%
#500
0"
1!
1#
0$
0%
